tuneSurvey/__init__.py
tuneSurvey/boostingLists.py
tuneSurvey/cleansing.py
tuneSurvey/forceCollect.py
tuneSurvey/mathExpand.py
tuneSurvey/skLists.py
tuneSurvey/subsetting.py
tuneSurvey/testExpand.py
tuneSurvey/tsReshape.py
tuneSurvey/tsVectorize.py
tuneSurvey/ts_torchLists.py
tunesurvey-0.0.5.dist-info/METADATA
tunesurvey-0.0.5.dist-info/WHEEL
tunesurvey-0.0.5.dist-info/licenses/LICENSE
tunesurvey-0.0.5.dist-info/RECORD
