Metadata-Version: 2.1
Name: tuneSurvey
Version: 0.0.5
Summary: Automatic tuning of machine learning models and surveying on the performance across subsets, variables, features, hyperparameters and pipelines
Project-URL: Homepage, https://pypi.org/project/tuneSurvey/0.0.1/
Project-URL: Bug Tracker, https://github.com/HaoLi111/tuneSurvey/issues
Author-email: Hao Li <lhrcplanes@qq.com>
License-File: LICENSE
Classifier: License :: OSI Approved :: MIT License
Classifier: Operating System :: OS Independent
Classifier: Programming Language :: Python :: 3
Requires-Python: >=3.6
